{
  "BOOKS_OUTPUT_MODE": "folder",
  "DESTINATION": "/books",
  "FILE_ORGANIZATION": "rename",
  "TEMPLATE_RENAME": "{Author} - {Title} ({Year})",
  "TEMPLATE_ORGANIZE": "{Author}/{Title} ({Year})",
  "HARDLINK_TORRENTS": false,
  "FILE_ORGANIZATION_AUDIOBOOK": "rename",
  "TEMPLATE_AUDIOBOOK_RENAME": "{Author} - {Title}",
  "TEMPLATE_AUDIOBOOK_ORGANIZE": "{Author}/{Title}",
  "HARDLINK_TORRENTS_AUDIOBOOK": true,
  "AUTO_OPEN_DOWNLOADS_SIDEBAR": false,
  "DOWNLOAD_TO_BROWSER": false,
  "MAX_CONCURRENT_DOWNLOADS": 3,
  "STATUS_TIMEOUT": 3600
}